regex_automata/__init__.py
regex_automata/common.py
regex_automata/errors.py
regex_automata/py.typed
regex_automata/automata/__init__.py
regex_automata/automata/nfa.py
regex_automata/automata/nfa_visualizer.py
regex_automata/automata/rangeset.py
regex_automata/parser/__init__.py
regex_automata/parser/ast.py
regex_automata/parser/ast_processor.py
regex_automata/parser/ast_visualizer.py
regex_automata/parser/parser.py
regex_automata/parser/tokenizer.py
regex_automata/parser/tokens.py
regex_automata/regex/__init__.py
regex_automata/regex/flags.py
regex_automata/regex/match.py
regex_automata/regex/nfa_builder.py
regex_automata/regex/nfa_evaluator.py
regex_automata/regex/pattern.py
regex_automata-0.3.1.dist-info/METADATA
regex_automata-0.3.1.dist-info/WHEEL
regex_automata-0.3.1.dist-info/licenses/LICENSE.txt
regex_automata-0.3.1.dist-info/RECORD
