Metadata-Version: 2.4
Name: regex-automata
Version: 0.3.1
Summary: Library for regular expressions using finite automata
Project-URL: Homepage, https://github.com/tkarabela/regex-automata
Project-URL: Repository, https://github.com/tkarabela/regex-automata.git
Project-URL: Issues, https://github.com/tkarabela/regex-automata/issues
Author-email: Tomas Karabela <tkarabela@seznam.cz>
License-Expression: MIT
License-File: LICENSE.txt
Keywords: finite automata,regex,regular expressions
Classifier: Development Status :: 3 - Alpha
Classifier: License :: OSI Approved :: MIT License
Classifier: Operating System :: OS Independent
Classifier: Programming Language :: Python :: 3
Classifier: Programming Language :: Python :: 3.11
Classifier: Programming Language :: Python :: 3.12
Classifier: Programming Language :: Python :: 3.13
Classifier: Programming Language :: Python :: 3.14
Classifier: Topic :: Text Processing
Classifier: Typing :: Typed
Requires-Python: >=3.11
Requires-Dist: graphviz~=0.21
